ChangeLog
LICENSE
MANIFEST.in
README.mediawiki
create_dev_installer.sh
create_release_installer.sh
latest-version
prepare_installer.sh
py-base
setup.py
docs/scanner_diagram.txt
docs/images/addr_bar.jpg
docs/images/admin_main.jpg
docs/images/admin_new_campaing.jpg
docs/images/admin_new_campaing.xcf
docs/images/configure_dongle.jpg
docs/images/configure_dongle.xwd
docs/images/django_admin.xwd
docs/images/django_campaign_details.jpg
docs/images/django_campaign_details.xwd
docs/images/django_files_details.jpg
docs/images/django_files_details.xwd
docs/images/django_rules_details.jpg
docs/images/django_rules_details.xwd
docs/images/known_dongles.jpg
docs/images/known_dongles.xwd
docs/images/login.jpg
docs/images/main.jpg
docs/images/server_status.jpg
docs/images/slax.jpg
docs/images/toolbar_admin.jpg
src/OpenProximity.egg-info/PKG-INFO
src/OpenProximity.egg-info/SOURCES.txt
src/OpenProximity.egg-info/dependency_links.txt
src/OpenProximity.egg-info/entry_points.txt
src/OpenProximity.egg-info/requires.txt
src/OpenProximity.egg-info/top_level.txt
src/OpenProximity.egg-info/zip-safe
src/locale/es/LC_MESSAGES/django.po
src/locale/it/LC_MESSAGES/django.po
src/locale/pl/LC_MESSAGES/django.po
src/microblog/__init__.py
src/microblog/sites.py
src/microblog/templates/log.html
src/microblog/templatetags/__init__.py
src/microblog/templatetags/microblog.py
src/openproximity/__init__.py
src/openproximity/admin.py
src/openproximity/context_processors.py
src/openproximity/forms.py
src/openproximity/models.py
src/openproximity/setup.py
src/openproximity/statistics.py
src/openproximity/template_loader.py
src/openproximity/treeview.py
src/openproximity/urls.py
src/openproximity/views.py
src/openproximity/lib/__init__.py
src/openproximity/lib/cherrypy.cfg
src/openproximity/lib/debug.cfg
src/openproximity/lib/default.cfg
src/openproximity/lib/django.cfg
src/openproximity/lib/lxmltool.py
src/openproximity/lib/manage.py
src/openproximity/lib/plug.py
src/openproximity/lib/preset.py
src/openproximity/lib/rpyc.cfg
src/openproximity/lib/schema.py
src/openproximity/lib/setpaths.py
src/openproximity/lib/settings.py
src/openproximity/lib/urls.py
src/openproximity/management/__init__.py
src/openproximity/management/commands/__init__.py
