Metadata-Version: 1.0
Name: OpenProximity
Version: 12.04.1
Summary: OpenProximity an OpenSource proximity marketing solution
Home-page: https://github.com/OpenProximity/web
Author: Naranjo Manuel Francisco
Author-email: manuel@aircable.net
License: Apache V2
Keywords: openproximity bluetooth obex proximity marketing
Platform: UNKNOWN
